{
  "country": "HU",
  "name": "Hungary",
  "wikipedia": "https://en.wikipedia.org/wiki/ISO_3166-2:HU",
  "dateAdded": "2026-07-21",
  "lastUpdated": "2026-07-21",
  "subdivisions": [
    {"code": "BA", "name": "Baranya", "category": "county"},
    {"code": "BC", "name": "Békéscsaba", "category": "city with county rights"},
    {"code": "BE", "name": "Békés", "category": "county"},
    {"code": "BK", "name": "Bács-Kiskun", "category": "county"},
    {"code": "BU", "name": "Budapest", "category": "capital city"},
    {"code": "BZ", "name": "Borsod-Abaúj-Zemplén", "category": "county"},
    {"code": "CS", "name": "Csongrád-Csanád", "category": "county"},
    {"code": "DE", "name": "Debrecen", "category": "city with county rights"},
    {"code": "DU", "name": "Dunaújváros", "category": "city with county rights"},
    {"code": "EG", "name": "Eger", "category": "city with county rights"},
    {"code": "ER", "name": "Érd", "category": "city with county rights"},
    {"code": "FE", "name": "Fejér", "category": "county"},
    {"code": "GS", "name": "Győr-Moson-Sopron", "category": "county"},
    {"code": "GY", "name": "Győr", "category": "city with county rights"},
    {"code": "HB", "name": "Hajdú-Bihar", "category": "county"},
    {"code": "HE", "name": "Heves", "category": "county"},
    {"code": "HV", "name": "Hódmezővásárhely", "category": "city with county rights"},
    {"code": "JN", "name": "Jász-Nagykun-Szolnok", "category": "county"},
    {"code": "KE", "name": "Komárom-Esztergom", "category": "county"},
    {"code": "KM", "name": "Kecskemét", "category": "city with county rights"},
    {"code": "KV", "name": "Kaposvár", "category": "city with county rights"},
    {"code": "MI", "name": "Miskolc", "category": "city with county rights"},
    {"code": "NK", "name": "Nagykanizsa", "category": "city with county rights"},
    {"code": "NO", "name": "Nógrád", "category": "county"},
    {"code": "NY", "name": "Nyíregyháza", "category": "city with county rights"},
    {"code": "PE", "name": "Pest", "category": "county"},
    {"code": "PS", "name": "Pécs", "category": "city with county rights"},
    {"code": "SD", "name": "Szeged", "category": "city with county rights"},
    {"code": "SF", "name": "Székesfehérvár", "category": "city with county rights"},
    {"code": "SH", "name": "Szombathely", "category": "city with county rights"},
    {"code": "SK", "name": "Szolnok", "category": "city with county rights"},
    {"code": "SN", "name": "Sopron", "category": "city with county rights"},
    {"code": "SO", "name": "Somogy", "category": "county"},
    {"code": "SS", "name": "Szekszárd", "category": "city with county rights"},
    {"code": "ST", "name": "Salgótarján", "category": "city with county rights"},
    {"code": "SZ", "name": "Szabolcs-Szatmár-Bereg", "category": "county"},
    {"code": "TB", "name": "Tatabánya", "category": "city with county rights"},
    {"code": "TO", "name": "Tolna", "category": "county"},
    {"code": "VA", "name": "Vas", "category": "county"},
    {"code": "VE", "name": "Veszprém", "category": "county"},
    {"code": "VM", "name": "Veszprém", "category": "city with county rights"},
    {"code": "ZA", "name": "Zala", "category": "county"},
    {"code": "ZE", "name": "Zalaegerszeg", "category": "city with county rights"}
  ]
}
